Metadata-Version: 1.0
Name: distributionsfortest
Version: 0.0
Summary: Gaussian and Binomial distributions
Home-page: UNKNOWN
Author: Kalky
Author-email: UNKNOWN
License: UNKNOWN
Platform: UNKNOWN
